naval/__init__.py
naval/crawl.py
naval/crawl_base.py
naval/crawler.py
naval/sources.py
naval/fetch/__init__.py
naval/fetch/bytes_fetch.py
naval/fetch/fetch.py
naval/fetch/fetch_base.py
naval/fetch/file_fetch.py
naval/fetch/master_fetch.py
naval/fetch/string_fetch.py
naval/fetch/web_fetch.py
naval/parse/__init__.py
naval/parse/docx_parse.py
naval/parse/html_parse.py
naval/parse/master_parse.py
naval/parse/parse.py
naval/parse/parse_base.py
naval/parse/pdf_parse.py
naval/parse/pptx_parse.py
naval/parse/text_parse.py
naval/text/__init__.py
naval/text/text.py
naval/text/text_section.py
naval/utility/__init__.py
naval/utility/container.py
naval/utility/directories.py
naval/utility/equality.py
naval/utility/files.py
naval/utility/metadata.py
naval/utility/section.py
navaly-0.0.1.dist-info/LICENSE
navaly-0.0.1.dist-info/METADATA
navaly-0.0.1.dist-info/WHEEL
navaly-0.0.1.dist-info/top_level.txt
navaly-0.0.1.dist-info/RECORD
