Metadata-Version: 2.1
Name: navaly
Version: 0.0.1
Summary: Downloads and extracts text, html from different formats
Home-page: https://github.com/Sekgobela-Kevin/naval
Author: Sekgobela Kevin
Author-email: kevinnoko23@gmail.com
Project-URL: Bug Tracker, https://github.com/Sekgobela-Kevin/naval/issues
Classifier: Intended Audience :: Developers
Classifier: Programming Language :: Python :: 3
Classifier: License :: OSI Approved :: MIT License
Classifier: Operating System :: OS Independent
Classifier: Topic :: Software Development :: Libraries :: Python Modules
License-File: LICENSE
Requires-Dist: urllib3
Requires-Dist: requests
Requires-Dist: beautifulsoup4
Requires-Dist: python-pptx
Requires-Dist: python-docx
Requires-Dist: PyDocX
Requires-Dist: pdfminer.six
